{
  "name": "Funeral Service: ING. Godwin Korshie-Sherrie",
  "avatar": "/thumbdadImage.png",
  "links": [
    {
      "href": "https://lsa-games.s3.eu-central-1.amazonaws.com/Draft.pdf",
      "title": "Download Brochure",
      "image": "/brochureEllipse.png"
    },
    {
      "href": "https://collections.kowri.app/main/1499",
      "title": "Donate with Card",
      "image": "/KowriLogo.png"
    },
    {
      "href": "tel:*227*1499%23",
      "title": "Donate with USSD",
      "image": "/ussd.png"
    }
  ],
  "socials": [
    {
      "href": "",
      "title": ""
    }
  ]
}
